{
  "version": "7",
  "dialect": "postgresql",
  "entries": [
    {
      "idx": 0,
      "version": "7",
      "when": 1748106171775,
      "tag": "0000_dazzling_avengers",
      "breakpoints": true
    },
    {
      "idx": 1,
      "version": "7",
      "when": 1748108809870,
      "tag": "0001_wealthy_lockheed",
      "breakpoints": true
    },
    {
      "idx": 2,
      "version": "7",
      "when": 1748158612505,
      "tag": "0002_melted_the_twelve",
      "breakpoints": true
    },
    {
      "idx": 3,
      "version": "7",
      "when": 1748160541698,
      "tag": "0003_cynical_albert_cleary",
      "breakpoints": true
    }
  ]
}